vk_cli/__init__.py
vk_cli/main.py
vk_cli/profile.py
vk_cli/shell.py
vk_cli/text.py
vk_cli/vk.py
vk_cli-0.1.1.dist-info/entry_points.txt
vk_cli-0.1.1.dist-info/WHEEL
vk_cli-0.1.1.dist-info/METADATA
vk_cli-0.1.1.dist-info/RECORD
