Metadata-Version: 2.1
Name: vk-cli
Version: 0.1.1
Summary: VK call api in console
Home-page: https://github.com/saalaus/vk-cli
Keywords: vk_api,vk,cli
Author: sergey
Author-email: saalaus@mail.ru
Requires-Python: >=3.9,<4.0
Classifier: Programming Language :: Python :: 3
Classifier: Programming Language :: Python :: 3.10
Classifier: Programming Language :: Python :: 3.9
Requires-Dist: Pygments (>=2.12.0,<3.0.0)
Requires-Dist: click (>=8.1.3,<9.0.0)
Requires-Dist: requests (>=2.28.1,<3.0.0)
Project-URL: Repository, https://github.com/saalaus/vk-cli
